di2008/__init__.py
di2008/instrument.py
di2008/version.py
di2008-0.4.9.dist-info/METADATA
di2008-0.4.9.dist-info/WHEEL
di2008-0.4.9.dist-info/license.txt
di2008-0.4.9.dist-info/top_level.txt
di2008-0.4.9.dist-info/RECORD
