Metadata-Version: 2.1
Name: di2008
Version: 0.4.9
Summary: Object-oriented API for DATAQ DI-2008
Home-page: https://github.com/slightlynybbled/di2008
Author: Jason R. Jones
Author-email: slightlynybbled@gmail.com
License: MIT
Platform: UNKNOWN
Classifier: License :: OSI Approved :: MIT License
Classifier: Development Status :: 3 - Alpha
Classifier: Programming Language :: Python
Classifier: Programming Language :: Python :: 3
Classifier: Programming Language :: Python :: 3.6
Classifier: Programming Language :: Python :: 3.7
Classifier: Programming Language :: Python :: Implementation :: CPython
Requires-Python: >=3.6.0
License-File: license.txt
Requires-Dist: pyserial (>=3.4)
